{
	"id": "2b95d0f6",
	"versionId": "7b3b2ea0",
	"eventDate": "01-02-2019",
	"lastUpdated": "2020-06-02T08:54:46.812+0000",
	"artist": {
		"mbid": "eeacb319-8d4c-48e0-80a0-944e71c375bf",
		"name": "Tesla",
		"sortName": "Tesla",
		"disambiguation": "hard rock band",
		"url": "https://www.setlist.fm/setlists/tesla-13d6b505.html"
	},
	"venue": {
		"id": "73d5828d",
		"name": "Mystic Showroom at Mystic Lake Casino",
		"city": {
			"id": "5042373",
			"name": "Prior Lake",
			"state": "Minnesota",
			"stateCode": "MN",
			"coords": {
				"lat": 44.7133,
				"long": -93.42273
			},
			"country": {
				"code": "US",
				"name": "United States"
			}
		},
		"url": "https://www.setlist.fm/venue/mystic-showroom-at-mystic-lake-casino-prior-lake-mn-usa-73d5828d.html"
	},
	"tour": {
		"name": "Shock"
	},
	"sets": {
		"set": [
			{
				"name": "",
				"encore": 0,
				"song": [
					{
						"name": "Welcome to the Jungle",
						"tape": true
					},
					{
						"name": "You Won’t Take Me Alive",
						"info": "live debut"
					},
					{
						"name": "Solution"
					},
					{
						"name": "Modern Day Cowboy"
					},
					{
						"name": "Be a Man",
						"info": "first time live since 1989"
					},
					{
						"name": "Heaven's Trail (No Way Out)"
					},
					{
						"name": "Breakin' Free"
					},
					{
						"name": "Miles Away"
					},
					{
						"name": "Changes"
					},
					{
						"name": "Stir It Up"
					},
					{
						"name": "Call It What You Want"
					},
					{
						"name": "What You Give"
					},
					{
						"name": "Shock",
						"info": "live debut"
					},
					{
						"name": "Edison's Medicine (Man Out of Time)"
					},
					{
						"name": "Love Song"
					},
					{
						"name": "Little Suzi"
					},
					{
						"name": "Signs"
					},
					{
						"name": "Happy Trails",
						"tape": true
					},
					{
						"name": "We Are the Champions",
						"tape": true
					}
				]
			}
		]
	},
	"url": "https://www.setlist.fm/setlist/tesla/2019/mystic-showroom-at-mystic-lake-casino-prior-lake-mn-2b95d0f6.html"
}